[{"Id":4,"Name":"Nguyễn Ngọc Hùng","Password":"password4","Email":"user1@example.com","Phone":"314324","DoB":"1992-11-10T00:00:00","Role":"Student"},{"Id":5,"Name":"Nguyen Nam","Password":"password5","Email":"user5@example.com","Phone":"777777777","DoB":"1985-04-30T00:00:00","Role":"Student"},{"Id":7,"Name":"Admin","Password":"adminpassword","Email":"admin@example.com","Phone":"123456789","DoB":"1990-01-01T00:00:00","Role":"Admin"},{"Id":8,"Name":"Lecture","Password":"lecturepassword","Email":"lecture@example.com","Phone":"987654321","DoB":"1980-05-05T00:00:00","Role":"Lecture"},{"Id":9,"Name":"Bao Thanh Thien VN","Password":"123@123a","Email":"bao@bao.bao","Phone":"1234","DoB":"1222-11-11T00:00:00","Role":"Student"},{"Id":10,"Name":"Nam Nguyen VN","Password":"123@123a","Email":"nam@nam.nam","Phone":"1234","DoB":"1111-11-11T00:00:00","Role":"Lecture"},{"Id":11,"Name":"Lmao Track Dont VN 1","Password":"1234","Email":"lmao1@lmao.lmao","Phone":"0000879878","DoB":"1111-11-11T00:00:00","Role":"Student"},{"Id":12,"Name":"Huy","Password":"12345678","Email":"whuyhaudauw@gmail.com","Phone":"0335639077","DoB":"2004-12-14T00:00:00","Role":"Student"},{"Id":13,"Name":"Huy2","Password":"123@123a","Email":"1@gmail.com","Phone":"0335639077","DoB":"2004-12-12T00:00:00","Role":"Student"},{"Id":14,"Name":"Huy","Password":"12345678","Email":"123@gmail.com","Phone":"0123456789","DoB":"2004-12-14T00:00:00","Role":"Student"},{"Id":15,"Name":"Phuc","Password":"123","Email":"phuc@gmail.com","Phone":"0123456789","DoB":"2004-11-20T00:00:00","Role":"Student"},{"Id":16,"Name":"Dat","Password":"123","Email":"dat@gmail.com","Phone":"0234156","DoB":"2005-12-14T00:00:00","Role":"Student"},{"Id":17,"Name":"Lan1","Password":"lan1","Email":"lan1@gmail.com","Phone":"0123456789","DoB":"2005-12-12T00:00:00","Role":"Student"},{"Id":18,"Name":"Lan2","Password":"lan2","Email":"lan2@gmail.com","Phone":"0123456789","DoB":"2004-12-12T00:00:00","Role":"Student"},{"Id":19,"Name":"Lan3","Password":"lan3","Email":"lan3@gmail.com","Phone":"0123456789","DoB":"2005-12-12T00:00:00","Role":"Student"}]